{"cameraMode":{"drawMode":0,"name":"Shaded","section":"Shading Mode"},"sceneLighting":true,"audioPlay":false,"sceneViewState":{"m_AlwaysRefresh":false,"showFog":true,"showSkybox":true,"showFlares":true,"showImageEffects":true,"showParticleSystems":true,"showVisualEffectGraphs":true,"m_FxEnabled":true},"in2DMode":false,"pivot":{"x":33.82459259033203,"y":-20.266374588012697,"z":55.83110809326172},"rotation":{"x":0.02614067867398262,"y":-0.9531491994857788,"z":0.2889137864112854,"w":0.08630002290010452},"size":36.99521255493164,"orthographic":false}